bag/__init__.py
bag/check_rst.py
bag/command.py
bag/console.py
bag/corrupt_image.py
bag/dump_mysql.py
bag/email_validator.py
bag/exceptions.py
bag/file_existence_manager.py
bag/html.py
bag/log.py
bag/monkeypatch.py
bag/more_codecs.py
bag/pathlib_complement.py
bag/reify.py
bag/reorder_po.py
bag/replace_many.py
bag/settings.py
bag/show_progress.py
bag/streams.py
bag/subcommand.py
bag/time.py
bag/git/__init__.py
bag/git/delete_old_branches.py
bag/locale/bag.pot
bag/locale/main_mapping.conf
bag/locale/pt_BR/LC_MESSAGES/bag.mo
bag/locale/pt_BR/LC_MESSAGES/bag.po
bag/spreadsheet/__init__.py
bag/spreadsheet/csv.py
bag/spreadsheet/excel.py
bag/sqlalchemy/__init__.py
bag/sqlalchemy/context.py
bag/sqlalchemy/created_changed.py
bag/sqlalchemy/json_col.py
bag/sqlalchemy/mediovaigel.py
bag/sqlalchemy/tricks.py
bag/text/__init__.py
bag/text/hash.py
bag/text/words.py
bag/web/__init__.py
bag/web/burla.py
bag/web/exceptions.py
bag/web/transecma.js
bag/web/transecma.py
bag/web/jinja2/bs-macros.jinja2
bag/web/pyramid/__init__.py
bag/web/pyramid/angular_csrf.py
bag/web/pyramid/burla.py
bag/web/pyramid/cache_buster.py
bag/web/pyramid/deform_view.py
bag/web/pyramid/locale.py
bag/web/pyramid/nav.py
bag/web/pyramid/plugins_manager.py
bag/web/pyramid/resources.py
bag/web/pyramid/robots.py
bag/web/pyramid/routes.py
bag/web/pyramid/views.py
bag/web/pyramid/apps/__init__.py
bag/web/pyramid/apps/views.py
bag-5.0.0.dist-info/LICENSE.rst
bag-5.0.0.dist-info/METADATA
bag-5.0.0.dist-info/WHEEL
bag-5.0.0.dist-info/entry_points.txt
bag-5.0.0.dist-info/top_level.txt
bag-5.0.0.dist-info/RECORD
