Metadata-Version: 2.1
Name: bag
Version: 5.0.0
Summary: A library for several purposes, including javascript i18n and stuff for the Pyramid web framework.
Home-page: https://github.com/nandoflorestan/bag
Author: Nando Florestan
Author-email: nandoflorestan@gmail.com
License: MIT
Keywords: python,pyramid,sqlalchemy,HTML,CSV,translation,i18n,internationalization,file hash,encoding,codecs,text,console
Platform: UNKNOWN
Classifier: Development Status :: 5 - Production/Stable
Classifier: Environment :: Console
Classifier: Environment :: Other Environment
Classifier: Intended Audience :: Developers
Classifier: License :: OSI Approved :: MIT License
Classifier: Operating System :: OS Independent
Classifier: Programming Language :: Python
Classifier: Programming Language :: Python :: 3
Classifier: Programming Language :: Python :: 3.7
Classifier: Programming Language :: Python :: 3.8
Classifier: Programming Language :: Python :: 3.9
Classifier: Programming Language :: Python :: Implementation :: CPython
Classifier: Programming Language :: Python :: Implementation :: PyPy
Classifier: Framework :: Pyramid
Classifier: Topic :: Database
Classifier: Topic :: Internet :: WWW/HTTP
Classifier: Topic :: Internet :: WWW/HTTP :: WSGI
Classifier: Topic :: Multimedia :: Graphics :: Graphics Conversion
Classifier: Topic :: Software Development :: Libraries :: Python Modules
Classifier: Topic :: Text Processing :: General
License-File: LICENSE.rst
Requires-Dist: polib
Requires-Dist: argh
